setup.py
funniest_dkm/__init__.py
funniest_dkm.egg-info/PKG-INFO
funniest_dkm.egg-info/SOURCES.txt
funniest_dkm.egg-info/dependency_links.txt
funniest_dkm.egg-info/not-zip-safe
funniest_dkm.egg-info/top_level.txt