Metadata-Version: 1.0
Name: funniest-dkm
Version: 0.1
Summary: The funniest joke in the world
Home-page: http://github.com/pascalmin/funniest
Author: Flying Circus
Author-email: pascalmin@gmail.com
License: MIT
Platform: UNKNOWN
